andrew_robot/__init__.py
andrew_robot/config.py
andrew_robot/led.py
andrew_robot/robot.py
andrew_robot/servo.py
andrew_robot/servo_defs.py
andrew_robot-0.0.1.dist-info/METADATA
andrew_robot-0.0.1.dist-info/WHEEL
andrew_robot-0.0.1.dist-info/licenses/LICENSE
andrew_robot-0.0.1.dist-info/RECORD
