Metadata-Version: 2.1
Name: andrew_robot
Version: 0.0.1
Summary: Control Andrew Robots from Andrew Alliance
Project-URL: Homepage, https://github.com/Brokemia/andrew-robot
Project-URL: Issues, https://github.com/Brokemia/andrew-robot/issues
Author: Cole Weber
Author-email: Brokemia <37253216+Brokemia@users.noreply.github.com>
License-Expression: MIT
License-File: LICENSE
Classifier: License :: OSI Approved :: MIT License
Classifier: Operating System :: OS Independent
Classifier: Programming Language :: Python :: 3
Requires-Python: >=3.8
